nestedjson2sql/__init__.py
nestedjson2sql/main.py
nestedjson2sql/src/__init__.py
nestedjson2sql/src/json_processor.py
nestedjson2sql/src/sql_processor.py
nestedjson2sql-0.1.1.dist-info/METADATA
nestedjson2sql-0.1.1.dist-info/WHEEL
nestedjson2sql-0.1.1.dist-info/entry_points.txt
nestedjson2sql-0.1.1.dist-info/top_level.txt
nestedjson2sql-0.1.1.dist-info/RECORD
