Metadata-Version: 2.1
Name: nestedjson2sql
Version: 0.1.1
Requires-Dist: json-relational >=0.0.3
Requires-Dist: sqlalchemy
Requires-Dist: pandas
